DogAge/__init__,py
DogAge/config.json
DogAge/dogage_validate.py
DogAge/mct2.py
dogage-0.0.5.dist-info/entry_points.txt
dogage-0.0.5.dist-info/WHEEL
dogage-0.0.5.dist-info/METADATA
dogage-0.0.5.dist-info/RECORD
